{
  "wbonds": [
    {
      "fields": [
        {
          "name": "event",
          "type": { "name": "Event", "fqelement": "dv-organization-event" },
          "of": { "name": "ShowEvent", "fqelement": "dv-organization-event" }
        },
        {
          "name": "resource",
          "type": { "name": "Resource", "fqelement": "dv-organization-allocator" },
          "of": { "name": "ShowConsumer", "fqelement": "dv-organization-allocator" }
        }
      ],
      "subfield": {
        "name": "group_meeting", "type": {
          "name": "ShowGroupMeeting", "fqelement": "dv-samples-morg"
        }, "of": {
          "name": "ShowGroupMeeting", "fqelement": "dv-samples-morg"
        }
      }
    },
    {
      "fields": [
        {
          "name": "allocation",
          "type": { "name": "Allocation", "fqelement": "dv-organization-allocator" },
          "of": { "name": "ShowConsumer", "fqelement": "dv-organization-allocator" }
        }
      ],
      "subfield": {
        "name": "selected_weekly_event", "type": {
          "name": "WeeklyEvent", "fqelement": "dv-organization-event"
        }, "of": {
          "name": "ChooseAndShowWeeklyEvent", "fqelement": "dv-organization-event"
        }
      }
    }
  ]
}
